{
  "$schema": "https://ui.shadcn.com/schema/registry-item.json",
  "name": "sidebar-10",
  "type": "registry:block",
  "author": "shadcn (https://ui.shadcn.com)",
  "description": "A sidebar in a popover.",
  "registryDependencies": [
    "sidebar",
    "breadcrumb",
    "separator",
    "popover",
    "collapsible",
    "dropdown-menu"
  ],
  "files": [
    {
      "path": "blocks/sidebar-10/page.tsx",
      "content": "import { AppSidebar } from \"@/registry/default/blocks/sidebar-10/components/app-sidebar\"\nimport { NavActions } from \"@/registry/default/blocks/sidebar-10/components/nav-actions\"\nimport {\n  Breadcrumb,\n  BreadcrumbItem,\n  BreadcrumbList,\n  BreadcrumbPage,\n} from \"@/registry/default/ui/breadcrumb\"\nimport { Separator } from \"@/registry/default/ui/separator\"\nimport {\n  SidebarInset,\n  SidebarProvider,\n  SidebarTrigger,\n} from \"@/registry/default/ui/sidebar\"\n\nexport default function Page() {\n  return (\n    <SidebarProvider>\n      <AppSidebar />\n      <SidebarInset>\n        <header className=\"flex h-14 shrink-0 items-center gap-2\">\n          <div className=\"flex flex-1 items-center gap-2 px-3\">\n            <SidebarTrigger />\n            <Separator orientation=\"vertical\" className=\"mr-2 h-4\" />\n            <Breadcrumb>\n              <BreadcrumbList>\n                <BreadcrumbItem>\n                  <BreadcrumbPage className=\"line-clamp-1\">\n                    Project Management & Task Tracking\n                  </BreadcrumbPage>\n                </BreadcrumbItem>\n              </BreadcrumbList>\n            </Breadcrumb>\n          </div>\n          <div className=\"ml-auto px-3\">\n            <NavActions />\n          </div>\n        </header>\n        <div className=\"flex flex-1 flex-col gap-4 px-4 py-10\">\n          <div className=\"mx-auto h-24 w-full max-w-3xl rounded-xl bg-muted/50\" />\n          <div className=\"mx-auto h-full w-full max-w-3xl rounded-xl bg-muted/50\" />\n        </div>\n      </SidebarInset>\n    </SidebarProvider>\n  )\n}\n",
      "type": "registry:page",
      "target": "app/dashboard/page.tsx"
    },
    {
      "path": "blocks/sidebar-10/components/app-sidebar.tsx",
      "content": "\"use client\"\n\nimport * as React from \"react\"\nimport {\n  AudioWaveform,\n  Blocks,\n  Calendar,\n  Command,\n  Home,\n  Inbox,\n  MessageCircleQuestion,\n  Search,\n  Settings2,\n  Sparkles,\n  Trash2,\n} from \"lucide-react\"\n\nimport { NavFavorites } from \"@/registry/default/blocks/sidebar-10/components/nav-favorites\"\nimport { NavMain } from \"@/registry/default/blocks/sidebar-10/components/nav-main\"\nimport { NavSecondary } from \"@/registry/default/blocks/sidebar-10/components/nav-secondary\"\nimport { NavWorkspaces } from \"@/registry/default/blocks/sidebar-10/components/nav-workspaces\"\nimport { TeamSwitcher } from \"@/registry/default/blocks/sidebar-10/components/team-switcher\"\nimport {\n  Sidebar,\n  SidebarContent,\n  SidebarHeader,\n  SidebarRail,\n} from \"@/registry/default/ui/sidebar\"\n\n// This is sample data.\nconst data = {\n  teams: [\n    {\n      name: \"Acme Inc\",\n      logo: Command,\n      plan: \"Enterprise\",\n    },\n    {\n      name: \"Acme Corp.\",\n      logo: AudioWaveform,\n      plan: \"Startup\",\n    },\n    {\n      name: \"Evil Corp.\",\n      logo: Command,\n      plan: \"Free\",\n    },\n  ],\n  navMain: [\n    {\n      title: \"Search\",\n      url: \"#\",\n      icon: Search,\n    },\n    {\n      title: \"Ask AI\",\n      url: \"#\",\n      icon: Sparkles,\n    },\n    {\n      title: \"Home\",\n      url: \"#\",\n      icon: Home,\n      isActive: true,\n    },\n    {\n      title: \"Inbox\",\n      url: \"#\",\n      icon: Inbox,\n      badge: \"10\",\n    },\n  ],\n  navSecondary: [\n    {\n      title: \"Calendar\",\n      url: \"#\",\n      icon: Calendar,\n    },\n    {\n      title: \"Settings\",\n      url: \"#\",\n      icon: Settings2,\n    },\n    {\n      title: \"Templates\",\n      url: \"#\",\n      icon: Blocks,\n    },\n    {\n      title: \"Trash\",\n      url: \"#\",\n      icon: Trash2,\n    },\n    {\n      title: \"Help\",\n      url: \"#\",\n      icon: MessageCircleQuestion,\n    },\n  ],\n  favorites: [\n    {\n      name: \"Project Management & Task Tracking\",\n      url: \"#\",\n      emoji: \"📊\",\n    },\n    {\n      name: \"Family Recipe Collection & Meal Planning\",\n      url: \"#\",\n      emoji: \"🍳\",\n    },\n    {\n      name: \"Fitness Tracker & Workout Routines\",\n      url: \"#\",\n      emoji: \"💪\",\n    },\n    {\n      name: \"Book Notes & Reading List\",\n      url: \"#\",\n      emoji: \"📚\",\n    },\n    {\n      name: \"Sustainable Gardening Tips & Plant Care\",\n      url: \"#\",\n      emoji: \"🌱\",\n    },\n    {\n      name: \"Language Learning Progress & Resources\",\n      url: \"#\",\n      emoji: \"🗣️\",\n    },\n    {\n      name: \"Home Renovation Ideas & Budget Tracker\",\n      url: \"#\",\n      emoji: \"🏠\",\n    },\n    {\n      name: \"Personal Finance & Investment Portfolio\",\n      url: \"#\",\n      emoji: \"💰\",\n    },\n    {\n      name: \"Movie & TV Show Watchlist with Reviews\",\n      url: \"#\",\n      emoji: \"🎬\",\n    },\n    {\n      name: \"Daily Habit Tracker & Goal Setting\",\n      url: \"#\",\n      emoji: \"✅\",\n    },\n  ],\n  workspaces: [\n    {\n      name: \"Personal Life Management\",\n      emoji: \"🏠\",\n      pages: [\n        {\n          name: \"Daily Journal & Reflection\",\n          url: \"#\",\n          emoji: \"📔\",\n        },\n        {\n          name: \"Health & Wellness Tracker\",\n          url: \"#\",\n          emoji: \"🍏\",\n        },\n        {\n          name: \"Personal Growth & Learning Goals\",\n          url: \"#\",\n          emoji: \"🌟\",\n        },\n      ],\n    },\n    {\n      name: \"Professional Development\",\n      emoji: \"💼\",\n      pages: [\n        {\n          name: \"Career Objectives & Milestones\",\n          url: \"#\",\n          emoji: \"🎯\",\n        },\n        {\n          name: \"Skill Acquisition & Training Log\",\n          url: \"#\",\n          emoji: \"🧠\",\n        },\n        {\n          name: \"Networking Contacts & Events\",\n          url: \"#\",\n          emoji: \"🤝\",\n        },\n      ],\n    },\n    {\n      name: \"Creative Projects\",\n      emoji: \"🎨\",\n      pages: [\n        {\n          name: \"Writing Ideas & Story Outlines\",\n          url: \"#\",\n          emoji: \"✍️\",\n        },\n        {\n          name: \"Art & Design Portfolio\",\n          url: \"#\",\n          emoji: \"🖼️\",\n        },\n        {\n          name: \"Music Composition & Practice Log\",\n          url: \"#\",\n          emoji: \"🎵\",\n        },\n      ],\n    },\n    {\n      name: \"Home Management\",\n      emoji: \"🏡\",\n      pages: [\n        {\n          name: \"Household Budget & Expense Tracking\",\n          url: \"#\",\n          emoji: \"💰\",\n        },\n        {\n          name: \"Home Maintenance Schedule & Tasks\",\n          url: \"#\",\n          emoji: \"🔧\",\n        },\n        {\n          name: \"Family Calendar & Event Planning\",\n          url: \"#\",\n          emoji: \"📅\",\n        },\n      ],\n    },\n    {\n      name: \"Travel & Adventure\",\n      emoji: \"🧳\",\n      pages: [\n        {\n          name: \"Trip Planning & Itineraries\",\n          url: \"#\",\n          emoji: \"🗺️\",\n        },\n        {\n          name: \"Travel Bucket List & Inspiration\",\n          url: \"#\",\n          emoji: \"🌎\",\n        },\n        {\n          name: \"Travel Journal & Photo Gallery\",\n          url: \"#\",\n          emoji: \"📸\",\n        },\n      ],\n    },\n  ],\n}\n\nexport function AppSidebar({ ...props }: React.ComponentProps<typeof Sidebar>) {\n  return (\n    <Sidebar className=\"border-r-0\" {...props}>\n      <SidebarHeader>\n        <TeamSwitcher teams={data.teams} />\n        <NavMain items={data.navMain} />\n      </SidebarHeader>\n      <SidebarContent>\n        <NavFavorites favorites={data.favorites} />\n        <NavWorkspaces workspaces={data.workspaces} />\n        <NavSecondary items={data.navSecondary} className=\"mt-auto\" />\n      </SidebarContent>\n      <SidebarRail />\n    </Sidebar>\n  )\n}\n",
      "type": "registry:component",
      "target": ""
    },
    {
      "path": "blocks/sidebar-10/components/nav-actions.tsx",
      "content": "\"use client\"\n\nimport * as React from \"react\"\nimport {\n  ArrowDown,\n  ArrowUp,\n  Bell,\n  Copy,\n  CornerUpLeft,\n  CornerUpRight,\n  FileText,\n  GalleryVerticalEnd,\n  LineChart,\n  Link,\n  MoreHorizontal,\n  Settings2,\n  Star,\n  Trash,\n  Trash2,\n} from \"lucide-react\"\n\nimport { Button } from \"@/registry/default/ui/button\"\nimport {\n  Popover,\n  PopoverContent,\n  PopoverTrigger,\n} from \"@/registry/default/ui/popover\"\nimport {\n  Sidebar,\n  SidebarContent,\n  SidebarGroup,\n  SidebarGroupContent,\n  SidebarMenu,\n  SidebarMenuButton,\n  SidebarMenuItem,\n} from \"@/registry/default/ui/sidebar\"\n\nconst data = [\n  [\n    {\n      label: \"Customize Page\",\n      icon: Settings2,\n    },\n    {\n      label: \"Turn into wiki\",\n      icon: FileText,\n    },\n  ],\n  [\n    {\n      label: \"Copy Link\",\n      icon: Link,\n    },\n    {\n      label: \"Duplicate\",\n      icon: Copy,\n    },\n    {\n      label: \"Move to\",\n      icon: CornerUpRight,\n    },\n    {\n      label: \"Move to Trash\",\n      icon: Trash2,\n    },\n  ],\n  [\n    {\n      label: \"Undo\",\n      icon: CornerUpLeft,\n    },\n    {\n      label: \"View analytics\",\n      icon: LineChart,\n    },\n    {\n      label: \"Version History\",\n      icon: GalleryVerticalEnd,\n    },\n    {\n      label: \"Show delete pages\",\n      icon: Trash,\n    },\n    {\n      label: \"Notifications\",\n      icon: Bell,\n    },\n  ],\n  [\n    {\n      label: \"Import\",\n      icon: ArrowUp,\n    },\n    {\n      label: \"Export\",\n      icon: ArrowDown,\n    },\n  ],\n]\n\nexport function NavActions() {\n  const [isOpen, setIsOpen] = React.useState(false)\n\n  React.useEffect(() => {\n    setIsOpen(true)\n  }, [])\n\n  return (\n    <div className=\"flex items-center gap-2 text-sm\">\n      <div className=\"hidden font-medium text-muted-foreground md:inline-block\">\n        Edit Oct 08\n      </div>\n      <Button variant=\"ghost\" size=\"icon\" className=\"h-7 w-7\">\n        <Star />\n      </Button>\n      <Popover open={isOpen} onOpenChange={setIsOpen}>\n        <PopoverTrigger asChild>\n          <Button\n            variant=\"ghost\"\n            size=\"icon\"\n            className=\"h-7 w-7 data-[state=open]:bg-accent\"\n          >\n            <MoreHorizontal />\n          </Button>\n        </PopoverTrigger>\n        <PopoverContent\n          className=\"w-56 overflow-hidden rounded-lg p-0\"\n          align=\"end\"\n        >\n          <Sidebar collapsible=\"none\" className=\"bg-transparent\">\n            <SidebarContent>\n              {data.map((group, index) => (\n                <SidebarGroup key={index} className=\"border-b last:border-none\">\n                  <SidebarGroupContent className=\"gap-0\">\n                    <SidebarMenu>\n                      {group.map((item, index) => (\n                        <SidebarMenuItem key={index}>\n                          <SidebarMenuButton>\n                            <item.icon /> <span>{item.label}</span>\n                          </SidebarMenuButton>\n                        </SidebarMenuItem>\n                      ))}\n                    </SidebarMenu>\n                  </SidebarGroupContent>\n                </SidebarGroup>\n              ))}\n            </SidebarContent>\n          </Sidebar>\n        </PopoverContent>\n      </Popover>\n    </div>\n  )\n}\n",
      "type": "registry:component",
      "target": ""
    },
    {
      "path": "blocks/sidebar-10/components/nav-favorites.tsx",
      "content": "\"use client\"\n\nimport {\n  ArrowUpRight,\n  Link,\n  MoreHorizontal,\n  StarOff,\n  Trash2,\n} from \"lucide-react\"\n\nimport {\n  DropdownMenu,\n  DropdownMenuContent,\n  DropdownMenuItem,\n  DropdownMenuSeparator,\n  DropdownMenuTrigger,\n} from \"@/registry/default/ui/dropdown-menu\"\nimport {\n  SidebarGroup,\n  SidebarGroupLabel,\n  SidebarMenu,\n  SidebarMenuAction,\n  SidebarMenuButton,\n  SidebarMenuItem,\n  useSidebar,\n} from \"@/registry/default/ui/sidebar\"\n\nexport function NavFavorites({\n  favorites,\n}: {\n  favorites: {\n    name: string\n    url: string\n    emoji: string\n  }[]\n}) {\n  const { isMobile } = useSidebar()\n\n  return (\n    <SidebarGroup className=\"group-data-[collapsible=icon]:hidden\">\n      <SidebarGroupLabel>Favorites</SidebarGroupLabel>\n      <SidebarMenu>\n        {favorites.map((item) => (\n          <SidebarMenuItem key={item.name}>\n            <SidebarMenuButton asChild>\n              <a href={item.url} title={item.name}>\n                <span>{item.emoji}</span>\n                <span>{item.name}</span>\n              </a>\n            </SidebarMenuButton>\n            <DropdownMenu>\n              <DropdownMenuTrigger asChild>\n                <SidebarMenuAction showOnHover>\n                  <MoreHorizontal />\n                  <span className=\"sr-only\">More</span>\n                </SidebarMenuAction>\n              </DropdownMenuTrigger>\n              <DropdownMenuContent\n                className=\"w-56 rounded-lg\"\n                side={isMobile ? \"bottom\" : \"right\"}\n                align={isMobile ? \"end\" : \"start\"}\n              >\n                <DropdownMenuItem>\n                  <StarOff className=\"text-muted-foreground\" />\n                  <span>Remove from Favorites</span>\n                </DropdownMenuItem>\n                <DropdownMenuSeparator />\n                <DropdownMenuItem>\n                  <Link className=\"text-muted-foreground\" />\n                  <span>Copy Link</span>\n                </DropdownMenuItem>\n                <DropdownMenuItem>\n                  <ArrowUpRight className=\"text-muted-foreground\" />\n                  <span>Open in New Tab</span>\n                </DropdownMenuItem>\n                <DropdownMenuSeparator />\n                <DropdownMenuItem>\n                  <Trash2 className=\"text-muted-foreground\" />\n                  <span>Delete</span>\n                </DropdownMenuItem>\n              </DropdownMenuContent>\n            </DropdownMenu>\n          </SidebarMenuItem>\n        ))}\n        <SidebarMenuItem>\n          <SidebarMenuButton className=\"text-sidebar-foreground/70\">\n            <MoreHorizontal />\n            <span>More</span>\n          </SidebarMenuButton>\n        </SidebarMenuItem>\n      </SidebarMenu>\n    </SidebarGroup>\n  )\n}\n",
      "type": "registry:component",
      "target": ""
    },
    {
      "path": "blocks/sidebar-10/components/nav-main.tsx",
      "content": "\"use client\"\n\nimport { type LucideIcon } from \"lucide-react\"\n\nimport {\n  SidebarMenu,\n  SidebarMenuButton,\n  SidebarMenuItem,\n} from \"@/registry/default/ui/sidebar\"\n\nexport function NavMain({\n  items,\n}: {\n  items: {\n    title: string\n    url: string\n    icon: LucideIcon\n    isActive?: boolean\n  }[]\n}) {\n  return (\n    <SidebarMenu>\n      {items.map((item) => (\n        <SidebarMenuItem key={item.title}>\n          <SidebarMenuButton asChild isActive={item.isActive}>\n            <a href={item.url}>\n              <item.icon />\n              <span>{item.title}</span>\n            </a>\n          </SidebarMenuButton>\n        </SidebarMenuItem>\n      ))}\n    </SidebarMenu>\n  )\n}\n",
      "type": "registry:component",
      "target": ""
    },
    {
      "path": "blocks/sidebar-10/components/nav-secondary.tsx",
      "content": "import React from \"react\"\nimport { type LucideIcon } from \"lucide-react\"\n\nimport {\n  SidebarGroup,\n  SidebarGroupContent,\n  SidebarMenu,\n  SidebarMenuBadge,\n  SidebarMenuButton,\n  SidebarMenuItem,\n} from \"@/registry/default/ui/sidebar\"\n\nexport function NavSecondary({\n  items,\n  ...props\n}: {\n  items: {\n    title: string\n    url: string\n    icon: LucideIcon\n    badge?: React.ReactNode\n  }[]\n} & React.ComponentPropsWithoutRef<typeof SidebarGroup>) {\n  return (\n    <SidebarGroup {...props}>\n      <SidebarGroupContent>\n        <SidebarMenu>\n          {items.map((item) => (\n            <SidebarMenuItem key={item.title}>\n              <SidebarMenuButton asChild>\n                <a href={item.url}>\n                  <item.icon />\n                  <span>{item.title}</span>\n                </a>\n              </SidebarMenuButton>\n              {item.badge && <SidebarMenuBadge>{item.badge}</SidebarMenuBadge>}\n            </SidebarMenuItem>\n          ))}\n        </SidebarMenu>\n      </SidebarGroupContent>\n    </SidebarGroup>\n  )\n}\n",
      "type": "registry:component",
      "target": ""
    },
    {
      "path": "blocks/sidebar-10/components/nav-workspaces.tsx",
      "content": "import { ChevronRight, MoreHorizontal, Plus } from \"lucide-react\"\n\nimport {\n  Collapsible,\n  CollapsibleContent,\n  CollapsibleTrigger,\n} from \"@/registry/default/ui/collapsible\"\nimport {\n  SidebarGroup,\n  SidebarGroupContent,\n  SidebarGroupLabel,\n  SidebarMenu,\n  SidebarMenuAction,\n  SidebarMenuButton,\n  SidebarMenuItem,\n  SidebarMenuSub,\n  SidebarMenuSubButton,\n  SidebarMenuSubItem,\n} from \"@/registry/default/ui/sidebar\"\n\nexport function NavWorkspaces({\n  workspaces,\n}: {\n  workspaces: {\n    name: string\n    emoji: React.ReactNode\n    pages: {\n      name: string\n      emoji: React.ReactNode\n    }[]\n  }[]\n}) {\n  return (\n    <SidebarGroup>\n      <SidebarGroupLabel>Workspaces</SidebarGroupLabel>\n      <SidebarGroupContent>\n        <SidebarMenu>\n          {workspaces.map((workspace) => (\n            <Collapsible key={workspace.name}>\n              <SidebarMenuItem>\n                <SidebarMenuButton asChild>\n                  <a href=\"#\">\n                    <span>{workspace.emoji}</span>\n                    <span>{workspace.name}</span>\n                  </a>\n                </SidebarMenuButton>\n                <CollapsibleTrigger asChild>\n                  <SidebarMenuAction\n                    className=\"left-2 bg-sidebar-accent text-sidebar-accent-foreground data-[state=open]:rotate-90\"\n                    showOnHover\n                  >\n                    <ChevronRight />\n                  </SidebarMenuAction>\n                </CollapsibleTrigger>\n                <SidebarMenuAction showOnHover>\n                  <Plus />\n                </SidebarMenuAction>\n                <CollapsibleContent>\n                  <SidebarMenuSub>\n                    {workspace.pages.map((page) => (\n                      <SidebarMenuSubItem key={page.name}>\n                        <SidebarMenuSubButton asChild>\n                          <a href=\"#\">\n                            <span>{page.emoji}</span>\n                            <span>{page.name}</span>\n                          </a>\n                        </SidebarMenuSubButton>\n                      </SidebarMenuSubItem>\n                    ))}\n                  </SidebarMenuSub>\n                </CollapsibleContent>\n              </SidebarMenuItem>\n            </Collapsible>\n          ))}\n          <SidebarMenuItem>\n            <SidebarMenuButton className=\"text-sidebar-foreground/70\">\n              <MoreHorizontal />\n              <span>More</span>\n            </SidebarMenuButton>\n          </SidebarMenuItem>\n        </SidebarMenu>\n      </SidebarGroupContent>\n    </SidebarGroup>\n  )\n}\n",
      "type": "registry:component",
      "target": ""
    },
    {
      "path": "blocks/sidebar-10/components/team-switcher.tsx",
      "content": "\"use client\"\n\nimport * as React from \"react\"\nimport { ChevronDown, Plus } from \"lucide-react\"\n\nimport {\n  DropdownMenu,\n  DropdownMenuContent,\n  DropdownMenuItem,\n  DropdownMenuLabel,\n  DropdownMenuSeparator,\n  DropdownMenuShortcut,\n  DropdownMenuTrigger,\n} from \"@/registry/default/ui/dropdown-menu\"\nimport {\n  SidebarMenu,\n  SidebarMenuButton,\n  SidebarMenuItem,\n} from \"@/registry/default/ui/sidebar\"\n\nexport function TeamSwitcher({\n  teams,\n}: {\n  teams: {\n    name: string\n    logo: React.ElementType\n    plan: string\n  }[]\n}) {\n  const [activeTeam, setActiveTeam] = React.useState(teams[0])\n\n  if (!activeTeam) {\n    return null\n  }\n\n  return (\n    <SidebarMenu>\n      <SidebarMenuItem>\n        <DropdownMenu>\n          <DropdownMenuTrigger asChild>\n            <SidebarMenuButton className=\"w-fit px-1.5\">\n              <div className=\"flex aspect-square size-5 items-center justify-center rounded-md bg-sidebar-primary text-sidebar-primary-foreground\">\n                <activeTeam.logo className=\"size-3\" />\n              </div>\n              <span className=\"truncate font-semibold\">{activeTeam.name}</span>\n              <ChevronDown className=\"opacity-50\" />\n            </SidebarMenuButton>\n          </DropdownMenuTrigger>\n          <DropdownMenuContent\n            className=\"w-64 rounded-lg\"\n            align=\"start\"\n            side=\"bottom\"\n            sideOffset={4}\n          >\n            <DropdownMenuLabel className=\"text-xs text-muted-foreground\">\n              Teams\n            </DropdownMenuLabel>\n            {teams.map((team, index) => (\n              <DropdownMenuItem\n                key={team.name}\n                onClick={() => setActiveTeam(team)}\n                className=\"gap-2 p-2\"\n              >\n                <div className=\"flex size-6 items-center justify-center rounded-sm border\">\n                  <team.logo className=\"size-4 shrink-0\" />\n                </div>\n                {team.name}\n                <DropdownMenuShortcut>⌘{index + 1}</DropdownMenuShortcut>\n              </DropdownMenuItem>\n            ))}\n            <DropdownMenuSeparator />\n            <DropdownMenuItem className=\"gap-2 p-2\">\n              <div className=\"flex size-6 items-center justify-center rounded-md border bg-background\">\n                <Plus className=\"size-4\" />\n              </div>\n              <div className=\"font-medium text-muted-foreground\">Add team</div>\n            </DropdownMenuItem>\n          </DropdownMenuContent>\n        </DropdownMenu>\n      </SidebarMenuItem>\n    </SidebarMenu>\n  )\n}\n",
      "type": "registry:component",
      "target": ""
    }
  ],
  "categories": [
    "sidebar",
    "dashboard"
  ]
}