{
  "$schema": "https://ui.shadcn.com/schema/registry-item.json",
  "name": "stepper-variants",
  "type": "registry:example",
  "author": "shadcn (https://ui.shadcn.com)",
  "registryDependencies": [
    "stepper"
  ],
  "files": [
    {
      "path": "examples/stepper-variants.tsx",
      "content": "import * as React from \"react\"\n\nimport { Label } from \"@/registry/new-york/ui/label\"\nimport { RadioGroup, RadioGroupItem } from \"@/registry/new-york/ui/radio-group\"\nimport {\n  Stepper,\n  StepperAction,\n  StepperControls,\n  StepperNavigation,\n  StepperPanel,\n  StepperStep,\n  StepperTitle,\n  defineStepper,\n} from \"@/registry/new-york/ui/stepper\"\n\ntype Variant = \"horizontal\" | \"vertical\" | \"circle\"\n\nconst stepperInstance = defineStepper(\n  {\n    id: \"step-1\",\n    title: \"Step 1\",\n  },\n  {\n    id: \"step-2\",\n    title: \"Step 2\",\n  },\n  {\n    id: \"step-3\",\n    title: \"Step 3\",\n  }\n)\n\nexport default function StepperVariants() {\n  const steps = stepperInstance.steps\n\n  const [variant, setVariant] = React.useState<Variant>(\"horizontal\")\n  return (\n    <div className=\"flex w-full flex-col gap-8\">\n      <RadioGroup\n        value={variant}\n        onValueChange={(value) => setVariant(value as Variant)}\n      >\n        <div className=\"flex items-center space-x-2\">\n          <RadioGroupItem value=\"horizontal\" id=\"horizontal-variant\" />\n          <Label htmlFor=\"horizontal-variant\">Horizontal</Label>\n        </div>\n        <div className=\"flex items-center space-x-2\">\n          <RadioGroupItem value=\"vertical\" id=\"vertical-variant\" />\n          <Label htmlFor=\"vertical-variant\">Vertical</Label>\n        </div>\n        <div className=\"flex items-center space-x-2\">\n          <RadioGroupItem value=\"circle\" id=\"circle-variant\" />\n          <Label htmlFor=\"circle-variant\">Circle</Label>\n        </div>\n      </RadioGroup>\n      {variant === \"horizontal\" && <HorizontalStepper />}\n      {variant === \"vertical\" && <VerticalStepper />}\n      {variant === \"circle\" && <CircleStepper />}\n    </div>\n  )\n}\n\nconst HorizontalStepper = () => {\n  const steps = stepperInstance.steps\n  return (\n    <Stepper\n      instance={stepperInstance}\n      className=\"space-y-4\"\n      variant=\"horizontal\"\n    >\n      {({ methods }) => (\n        <>\n          <StepperNavigation>\n            {steps.map((step) => (\n              <StepperStep\n                key={step.id}\n                of={step}\n                onClick={() => methods.goTo(step.id)}\n              >\n                <StepperTitle>{step.title}</StepperTitle>\n              </StepperStep>\n            ))}\n          </StepperNavigation>\n          {steps.map((step) => (\n            <StepperPanel\n              key={step.id}\n              when={step}\n              className=\"h-[200px] content-center rounded border bg-slate-50 p-8\"\n            >\n              {({ step }) => (\n                <p className=\"text-xl font-normal\">Content for {step.id}</p>\n              )}\n            </StepperPanel>\n          ))}\n          <StepperControls>\n            <StepperAction action=\"prev\">Previous</StepperAction>\n            <StepperAction action=\"next\">Next</StepperAction>\n            <StepperAction action=\"reset\">Reset</StepperAction>\n          </StepperControls>\n        </>\n      )}\n    </Stepper>\n  )\n}\n\nconst VerticalStepper = () => {\n  const steps = stepperInstance.steps\n  return (\n    <Stepper\n      instance={stepperInstance}\n      className=\"space-y-4\"\n      variant=\"vertical\"\n    >\n      {({ methods }) => (\n        <>\n          <StepperNavigation>\n            {steps.map((step) => (\n              <StepperStep\n                key={step.id}\n                of={step}\n                onClick={() => methods.goTo(step.id)}\n              >\n                <StepperTitle>{step.title}</StepperTitle>\n                <StepperPanel\n                  key={step.id}\n                  when={step}\n                  className=\"h-[200px] content-center rounded border bg-slate-50 p-8\"\n                >\n                  {({ step }) => (\n                    <p className=\"text-xl font-normal\">Content for {step.id}</p>\n                  )}\n                </StepperPanel>\n              </StepperStep>\n            ))}\n          </StepperNavigation>\n          <StepperControls>\n            <StepperAction action=\"prev\">Previous</StepperAction>\n            <StepperAction action=\"next\">Next</StepperAction>\n            <StepperAction action=\"reset\">Reset</StepperAction>\n          </StepperControls>\n        </>\n      )}\n    </Stepper>\n  )\n}\n\nconst CircleStepper = () => {\n  const steps = stepperInstance.steps\n  return (\n    <Stepper instance={stepperInstance} className=\"space-y-4\" variant=\"circle\">\n      {({ methods }) => (\n        <>\n          <StepperNavigation>\n            <StepperStep of={methods.current}>\n              <StepperTitle>{methods.current.title}</StepperTitle>\n            </StepperStep>\n          </StepperNavigation>\n          {steps.map((step) => (\n            <StepperPanel\n              key={step.id}\n              when={step}\n              className=\"h-[200px] content-center rounded border bg-slate-50 p-8\"\n            >\n              {({ step }) => (\n                <p className=\"text-xl font-normal\">Content for {step.id}</p>\n              )}\n            </StepperPanel>\n          ))}\n          <StepperControls>\n            <StepperAction action=\"prev\">Previous</StepperAction>\n            <StepperAction action=\"next\">Next</StepperAction>\n            <StepperAction action=\"reset\">Reset</StepperAction>\n          </StepperControls>\n        </>\n      )}\n    </Stepper>\n  )\n}\n",
      "type": "registry:example",
      "target": ""
    }
  ]
}