{
  "$schema": "https://ui.shadcn.com/schema/registry-item.json",
  "name": "button-demo",
  "type": "registry:example",
  "author": "shadcn (https://ui.shadcn.com)",
  "registryDependencies": [
    "button"
  ],
  "files": [
    {
      "path": "examples/button-demo.tsx",
      "content": "import { Button } from \"@/registry/default/ui/button\"\r\n\r\nexport default function ButtonDemo() {\r\n  return <Button>Button</Button>\r\n}\r\n",
      "type": "registry:example",
      "target": ""
    }
  ]
}