{
  "$schema": "https://ui.shadcn.com/schema/registry-item.json",
  "name": "calendar-25",
  "type": "registry:block",
  "author": "shadcn (https://ui.shadcn.com)",
  "description": "Date and Time range picker",
  "registryDependencies": [
    "calendar",
    "popover",
    "button",
    "label"
  ],
  "files": [
    {
      "path": "blocks/calendar-25.tsx",
      "content": "\"use client\"\n\nimport * as React from \"react\"\nimport { ChevronDownIcon } from \"lucide-react\"\n\nimport { Button } from \"@/registry/default/ui/button\"\nimport { Calendar } from \"@/registry/default/ui/calendar\"\nimport { Input } from \"@/registry/default/ui/input\"\nimport { Label } from \"@/registry/default/ui/label\"\nimport {\n  Popover,\n  PopoverContent,\n  PopoverTrigger,\n} from \"@/registry/default/ui/popover\"\n\nexport default function Calendar25() {\n  const [open, setOpen] = React.useState(false)\n  const [date, setDate] = React.useState<Date | undefined>(undefined)\n\n  return (\n    <div className=\"flex flex-col gap-6\">\n      <div className=\"flex flex-col gap-3\">\n        <Label htmlFor=\"date\" className=\"px-1\">\n          Date\n        </Label>\n        <Popover open={open} onOpenChange={setOpen}>\n          <PopoverTrigger asChild>\n            <Button\n              variant=\"outline\"\n              id=\"date\"\n              className=\"w-full justify-between font-normal\"\n            >\n              {date ? date.toLocaleDateString() : \"Select date\"}\n              <ChevronDownIcon />\n            </Button>\n          </PopoverTrigger>\n          <PopoverContent className=\"w-auto overflow-hidden p-0\" align=\"start\">\n            <Calendar\n              mode=\"single\"\n              selected={date}\n              captionLayout=\"dropdown\"\n              onSelect={(date) => {\n                setDate(date)\n                setOpen(false)\n              }}\n            />\n          </PopoverContent>\n        </Popover>\n      </div>\n      <div className=\"flex gap-4\">\n        <div className=\"flex flex-col gap-3\">\n          <Label htmlFor=\"time-from\" className=\"px-1\">\n            From\n          </Label>\n          <Input\n            type=\"time\"\n            id=\"time-from\"\n            step=\"1\"\n            defaultValue=\"10:30:00\"\n            className=\"bg-background appearance-none [&::-webkit-calendar-picker-indicator]:hidden [&::-webkit-calendar-picker-indicator]:appearance-none\"\n          />\n        </div>\n        <div className=\"flex flex-col gap-3\">\n          <Label htmlFor=\"time-to\" className=\"px-1\">\n            To\n          </Label>\n          <Input\n            type=\"time\"\n            id=\"time-to\"\n            step=\"1\"\n            defaultValue=\"12:30:00\"\n            className=\"bg-background appearance-none [&::-webkit-calendar-picker-indicator]:hidden [&::-webkit-calendar-picker-indicator]:appearance-none\"\n          />\n        </div>\n      </div>\n    </div>\n  )\n}\n",
      "type": "registry:component",
      "target": ""
    }
  ],
  "meta": {
    "iframeHeight": "600px",
    "container": "w-full bg-surface min-h-svh flex px-6 py-12 items-start md:pt-20 justify-center min-w-0 xl:py-24",
    "mobile": "component"
  },
  "categories": [
    "calendar",
    "date"
  ]
}