{
  "$schema": "https://ui.shadcn.com/schema/registry-item.json",
  "name": "faq-04",
  "type": "registry:block",
  "author": "shadcn (https://ui.shadcn.com)",
  "description": "Accordion with sidebar groups",
  "registryDependencies": [
    "accordion"
  ],
  "files": [
    {
      "path": "blocks/faq-04/page.tsx",
      "content": "import { FAQ } from \"@/registry/default/blocks/faq-04/components/faq\"\n\nexport default function LoginPage() {\n  return (\n    <div className=\"flex min-h-svh flex-col\">\n      <FAQ />\n    </div>\n  )\n}\n",
      "type": "registry:page",
      "target": "app/faq/page.tsx"
    },
    {
      "path": "blocks/faq-04/components/faq.tsx",
      "content": "import {\n  Accordion,\n  AccordionContent,\n  AccordionItem,\n  AccordionTrigger,\n} from \"@/registry/default/ui/accordion\"\n\nconst groups = [\n  {\n    title: \"General FAQs\",\n    items: [\n      {\n        label: \"What is the Force?\",\n        content:\n          \"The Force is a mystical energy field that binds the galaxy together.\",\n        value: \"item-1\",\n      },\n      {\n        label: \"Who are the Jedi and what is their purpose?\",\n        content:\n          \"The Jedi are peacekeepers of the galaxy who use the Force for good. Their purpose is to protect and maintain peace.\",\n        value: \"item-2\",\n      },\n      {\n        label: \"Who are the Sith and what are their goals?\",\n        content:\n          \"The Sith are followers of the dark side who seek power and control. Their ultimate goal is to dominate the galaxy.\",\n        value: \"item-3\",\n      },\n    ],\n  },\n  {\n    title: \"Other FAQs\",\n    items: [\n      {\n        label: \"Yoda, who is?\",\n        content:\n          \"A wise and powerful Jedi Master, Yoda is. Trained many Jedi, he has.\",\n        value: \"item-4\",\n      },\n      {\n        label: \"What is the Death Star?\",\n        content:\n          \"The Death Star is a massive space station and superweapon capable of destroying planets.\",\n        value: \"item-5\",\n      },\n      {\n        label: \"What is the Millennium Falcon?\",\n        content:\n          \"The Millennium Falcon is a legendary starship flown by Han Solo and Chewbacca.\",\n        value: \"item-6\",\n      },\n    ],\n  },\n]\n\nexport function FAQ() {\n  return (\n    <div className=\"flex flex-col bg-background space-y-20 p-6 md:p-4 max-w-7xl w-full m-auto\">\n      <h2 className=\"text-center font-bold text-3xl lg:text-4xl\">\n        Frequently Asked Questions\n      </h2>\n      {groups.map((group) => (\n        <div key={group.title} className=\"flex flex-col lg:grid lg:grid-cols-3\">\n          <div className=\"text-2xl lg:text-3xl font-semibold col-span-1 mb-8\">\n            {group.title}\n          </div>\n          <Accordion\n            type=\"single\"\n            collapsible\n            className=\"col-span-2 w-full gap-y-2 flex flex-col\"\n          >\n            {group.items.map((item) => (\n              <AccordionItem\n                key={item.value}\n                value={item.value}\n                className=\"first-of-type:border-t\"\n              >\n                <AccordionTrigger className=\"text-primary text-xl font-normal [&>svg]:h-7 [&>svg]:w-7 hover:no-underline\">\n                  {item.label}\n                </AccordionTrigger>\n                <AccordionContent className=\"text-muted-foreground text-base\">\n                  {item.content}\n                </AccordionContent>\n              </AccordionItem>\n            ))}\n          </Accordion>\n        </div>\n      ))}\n    </div>\n  )\n}\n",
      "type": "registry:component",
      "target": ""
    }
  ],
  "categories": [
    "faq"
  ]
}