{
  "$schema": "https://ui.shadcn.com/schema/registry-item.json",
  "name": "pagination-demo",
  "type": "registry:example",
  "author": "shadcn (https://ui.shadcn.com)",
  "registryDependencies": [
    "pagination"
  ],
  "files": [
    {
      "path": "examples/pagination-demo.tsx",
      "content": "import {\r\n  Pagination,\r\n  PaginationContent,\r\n  PaginationEllipsis,\r\n  PaginationItem,\r\n  PaginationLink,\r\n  PaginationNext,\r\n  PaginationPrevious,\r\n} from \"@/registry/default/ui/pagination\"\r\n\r\nexport default function PaginationDemo() {\r\n  return (\r\n    <Pagination>\r\n      <PaginationContent>\r\n        <PaginationItem>\r\n          <PaginationPrevious href=\"#\" />\r\n        </PaginationItem>\r\n        <PaginationItem>\r\n          <PaginationLink href=\"#\">1</PaginationLink>\r\n        </PaginationItem>\r\n        <PaginationItem>\r\n          <PaginationLink href=\"#\" isActive>\r\n            2\r\n          </PaginationLink>\r\n        </PaginationItem>\r\n        <PaginationItem>\r\n          <PaginationLink href=\"#\">3</PaginationLink>\r\n        </PaginationItem>\r\n        <PaginationItem>\r\n          <PaginationEllipsis />\r\n        </PaginationItem>\r\n        <PaginationItem>\r\n          <PaginationNext href=\"#\" />\r\n        </PaginationItem>\r\n      </PaginationContent>\r\n    </Pagination>\r\n  )\r\n}\r\n",
      "type": "registry:example",
      "target": ""
    }
  ]
}