{
  "$schema": "https://ui.shadcn.com/schema/registry-item.json",
  "name": "spinner-size",
  "title": "Spinner Size",
  "registryDependencies": [
    "spinner"
  ],
  "files": [
    {
      "path": "registry/base-vega/demo/spinner-size.tsx",
      "content": "import { Spinner } from \"@/registry/base-vega/ui/spinner\"\n\nexport function SpinnerSize() {\n  return (\n    <div className=\"flex items-center gap-6\">\n      <Spinner className=\"size-3\" />\n      <Spinner className=\"size-4\" />\n      <Spinner className=\"size-6\" />\n      <Spinner className=\"size-8\" />\n    </div>\n  )\n}\n",
      "type": "registry:example"
    }
  ],
  "type": "registry:example"
}