{
  "$schema": "https://ui.shadcn.com/schema/registry-item.json",
  "name": "textarea-demo",
  "title": "Textarea Demo",
  "registryDependencies": [
    "textarea"
  ],
  "files": [
    {
      "path": "registry/base-vega/demo/textarea-demo.tsx",
      "content": "import { Textarea } from \"@/registry/base-nova/ui/textarea\"\n\nexport default function TextareaDemo() {\n  return <Textarea placeholder=\"Type your message here.\" />\n}\n",
      "type": "registry:example"
    }
  ],
  "type": "registry:example"
}