{
  "$schema": "https://ui.shadcn.com/schema/registry-item.json",
  "name": "command-demo",
  "type": "registry:example",
  "author": "shadcn (https://ui.shadcn.com)",
  "registryDependencies": [
    "command"
  ],
  "files": [
    {
      "path": "examples/command-demo.tsx",
      "content": "import {\n  Calculator,\n  Calendar,\n  CreditCard,\n  Settings,\n  Smile,\n  User,\n} from \"lucide-react\"\n\nimport {\n  Command,\n  CommandEmpty,\n  CommandGroup,\n  CommandInput,\n  CommandItem,\n  CommandList,\n  CommandSeparator,\n  CommandShortcut,\n} from \"@/registry/default/ui/command\"\n\nexport default function CommandDemo() {\n  return (\n    <Command className=\"rounded-lg border shadow-md md:min-w-[450px]\">\n      <CommandInput placeholder=\"Type a command or search...\" />\n      <CommandList>\n        <CommandEmpty>No results found.</CommandEmpty>\n        <CommandGroup heading=\"Suggestions\">\n          <CommandItem>\n            <Calendar />\n            <span>Calendar</span>\n          </CommandItem>\n          <CommandItem>\n            <Smile />\n            <span>Search Emoji</span>\n          </CommandItem>\n          <CommandItem disabled>\n            <Calculator />\n            <span>Calculator</span>\n          </CommandItem>\n        </CommandGroup>\n        <CommandSeparator />\n        <CommandGroup heading=\"Settings\">\n          <CommandItem>\n            <User />\n            <span>Profile</span>\n            <CommandShortcut>⌘P</CommandShortcut>\n          </CommandItem>\n          <CommandItem>\n            <CreditCard />\n            <span>Billing</span>\n            <CommandShortcut>⌘B</CommandShortcut>\n          </CommandItem>\n          <CommandItem>\n            <Settings />\n            <span>Settings</span>\n            <CommandShortcut>⌘S</CommandShortcut>\n          </CommandItem>\n        </CommandGroup>\n      </CommandList>\n    </Command>\n  )\n}\n",
      "type": "registry:example",
      "target": ""
    }
  ]
}