{
  "$schema": "https://ui.shadcn.com/schema/registry-item.json",
  "name": "button-demo",
  "title": "Button Demo",
  "dependencies": [],
  "registryDependencies": [
    "button"
  ],
  "files": [
    {
      "path": "registry/ember-nova/examples/button-demo.gts",
      "content": "import { Button } from '@/ui/button';\n\nimport ArrowUpIcon from '~icons/lucide/arrow-up';\n\n<template>\n  <div class=\"flex flex-wrap items-center gap-2 md:flex-row\">\n    <Button @variant=\"outline\">Button</Button>\n    <Button @size=\"icon\" @variant=\"outline\" aria-label=\"Submit\">\n      <ArrowUpIcon />\n    </Button>\n  </div>\n</template>\n",
      "type": "registry:example"
    }
  ],
  "type": "registry:example"
}