{
  "$schema": "https://ui.shadcn.com/schema/registry-item.json",
  "name": "menubar-demo",
  "title": "Menubar Demo",
  "registryDependencies": [
    "menubar"
  ],
  "files": [
    {
      "path": "registry/svelte-force-ui/examples/menubar-demo.svelte",
      "content": "<script lang=\"ts\">\n  import * as Menubar from \"$lib/registry/ui/menubar/index.js\"\n\n  let bookmarks = $state(false)\n  let fullUrls = $state(true)\n  let profileRadioValue = $state(\"benoit\")\n</script>\n\n<Menubar.Root>\n  <Menubar.Menu>\n    <Menubar.Trigger>File</Menubar.Trigger>\n    <Menubar.Content>\n      <Menubar.Item>\n        New Tab <Menubar.Shortcut>⌘T</Menubar.Shortcut>\n      </Menubar.Item>\n      <Menubar.Item>\n        New Window <Menubar.Shortcut>⌘N</Menubar.Shortcut>\n      </Menubar.Item>\n      <Menubar.Item>New Incognito Window</Menubar.Item>\n      <Menubar.Separator />\n      <Menubar.Sub>\n        <Menubar.SubTrigger>Share</Menubar.SubTrigger>\n        <Menubar.SubContent>\n          <Menubar.Item>Email link</Menubar.Item>\n          <Menubar.Item>Messages</Menubar.Item>\n          <Menubar.Item>Notes</Menubar.Item>\n        </Menubar.SubContent>\n      </Menubar.Sub>\n      <Menubar.Separator />\n      <Menubar.Item>\n        Print... <Menubar.Shortcut>⌘P</Menubar.Shortcut>\n      </Menubar.Item>\n    </Menubar.Content>\n  </Menubar.Menu>\n  <Menubar.Menu>\n    <Menubar.Trigger>Edit</Menubar.Trigger>\n    <Menubar.Content>\n      <Menubar.Item>\n        Undo <Menubar.Shortcut>⌘Z</Menubar.Shortcut>\n      </Menubar.Item>\n      <Menubar.Item>\n        Redo <Menubar.Shortcut>⇧⌘Z</Menubar.Shortcut>\n      </Menubar.Item>\n      <Menubar.Separator />\n      <Menubar.Sub>\n        <Menubar.SubTrigger>Find</Menubar.SubTrigger>\n        <Menubar.SubContent>\n          <Menubar.Item>Search the web</Menubar.Item>\n          <Menubar.Separator />\n          <Menubar.Item>Find...</Menubar.Item>\n          <Menubar.Item>Find Next</Menubar.Item>\n          <Menubar.Item>Find Previous</Menubar.Item>\n        </Menubar.SubContent>\n      </Menubar.Sub>\n      <Menubar.Separator />\n      <Menubar.Item>Cut</Menubar.Item>\n      <Menubar.Item>Copy</Menubar.Item>\n      <Menubar.Item>Paste</Menubar.Item>\n    </Menubar.Content>\n  </Menubar.Menu>\n  <Menubar.Menu>\n    <Menubar.Trigger>View</Menubar.Trigger>\n    <Menubar.Content>\n      <Menubar.CheckboxItem bind:checked={bookmarks}\n        >Always Show Bookmarks Bar</Menubar.CheckboxItem\n      >\n      <Menubar.CheckboxItem bind:checked={fullUrls}>\n        Always Show Full URLs\n      </Menubar.CheckboxItem>\n      <Menubar.Separator />\n      <Menubar.Item inset>\n        Reload <Menubar.Shortcut>⌘R</Menubar.Shortcut>\n      </Menubar.Item>\n      <Menubar.Item inset>\n        Force Reload <Menubar.Shortcut>⇧⌘R</Menubar.Shortcut>\n      </Menubar.Item>\n      <Menubar.Separator />\n      <Menubar.Item inset>Toggle Fullscreen</Menubar.Item>\n      <Menubar.Separator />\n      <Menubar.Item inset>Hide Sidebar</Menubar.Item>\n    </Menubar.Content>\n  </Menubar.Menu>\n  <Menubar.Menu>\n    <Menubar.Trigger>Profiles</Menubar.Trigger>\n    <Menubar.Content>\n      <Menubar.RadioGroup bind:value={profileRadioValue}>\n        <Menubar.RadioItem value=\"andy\">Andy</Menubar.RadioItem>\n        <Menubar.RadioItem value=\"benoit\">Benoit</Menubar.RadioItem>\n        <Menubar.RadioItem value=\"Luis\">Luis</Menubar.RadioItem>\n      </Menubar.RadioGroup>\n      <Menubar.Separator />\n      <Menubar.Item inset>Edit...</Menubar.Item>\n      <Menubar.Separator />\n      <Menubar.Item inset>Add Profile...</Menubar.Item>\n    </Menubar.Content>\n  </Menubar.Menu>\n</Menubar.Root>\n",
      "type": "registry:example"
    }
  ],
  "type": "registry:example"
}